better_fastapi_discord/__init__.py
better_fastapi_discord/client.py
better_fastapi_discord/config.py
better_fastapi_discord/exceptions.py
better_fastapi_discord/models/__init__.py
better_fastapi_discord/models/guild.py
better_fastapi_discord/models/role.py
better_fastapi_discord/models/user.py
better_fastapi_discord-0.2.5.dist-info/LICENSE
better_fastapi_discord-0.2.5.dist-info/METADATA
better_fastapi_discord-0.2.5.dist-info/WHEEL
better_fastapi_discord-0.2.5.dist-info/top_level.txt
better_fastapi_discord-0.2.5.dist-info/RECORD
